gattlib/helpers.py
gattlib/uuid.py
gattlib/adapter.py
gattlib/device.py
gattlib/__init__.py
gattlib/libgattlib.so
gattlib/mainloop.py
gattlib/_version.py
gattlib/gatt.py
gattlib/exception.py
gattlib_py-0.7.2.dist-info/METADATA
gattlib_py-0.7.2.dist-info/RECORD
gattlib_py-0.7.2.dist-info/top_level.txt
gattlib_py-0.7.2.dist-info/WHEEL
gattlib_py.libs/libffi-56a10382.so.6.0.1
gattlib_py.libs/libblkid-acbe2080.so.1.1.0
gattlib_py.libs/libselinux-c9aa910a.so.1
gattlib_py.libs/libuuid-0a7b20a1.so.1.3.0
gattlib_py.libs/libmount-bc906051.so.1.1.0
gattlib_py.libs/libgio-2-273f8b3e.0.so.0.5600.1
gattlib_py.libs/libgmodule-2-590b35e7.0.so.0.5600.1
gattlib_py.libs/libpcre-863f8bd5.so.1.2.0
