Metadata-Version: 2.1
Name: gattlib-py
Version: 0.7.2
Summary: Python wrapper for gattlib library
Home-page: https://github.com/labapart/gattlib/gattlib-py
Author: Olivier Martin
Author-email: olivier@labapart.com
License: UNKNOWN
Platform: UNKNOWN
Requires-Dist: setuptools
Requires-Dist: PyGObject (>=3.44.0)
